carta/__init__.py
carta/__main__.py
carta-1.3.3.dist-info/LICENSE
carta-1.3.3.dist-info/WHEEL
carta-1.3.3.dist-info/METADATA
carta-1.3.3.dist-info/RECORD
